cropperjs/__init__.py
cropperjs/fields.py
cropperjs/models.py
cropperjs/utils.py
cropperjs/widgets.py
cropperjs/locale/pt_BR/LC_MESSAGES/django.mo
cropperjs/locale/pt_BR/LC_MESSAGES/django.po
cropperjs/static/css/cropper.extra.css
cropperjs/static/css/cropper.min.css
cropperjs/static/img/icon-aspect.png
cropperjs/static/img/icon-reset.png
cropperjs/static/img/icon-rotate-left.png
cropperjs/static/img/icon-rotate-right.png
cropperjs/static/img/icon-zoom-in.png
cropperjs/static/img/icon-zoom-out.png
cropperjs/static/js/cropper.extra.js
cropperjs/static/js/cropper.min.js
cropperjs/templates/cropperjs/widgets/cropperjs.html
testapp/manage.py
testapp/apps/__init__.py
testapp/apps/testmodels/__init__.py
testapp/apps/testmodels/admin.py
testapp/apps/testmodels/apps.py
testapp/apps/testmodels/models.py
testapp/apps/testmodels/tests.py
testapp/apps/testmodels/migrations/0001_initial.py
testapp/apps/testmodels/migrations/__init__.py
testapp/conf/__init__.py
testapp/conf/settings.py
testapp/conf/urls.py
testapp/conf/wsgi.py
django_cropperjs2-0.0.7.dist-info/LICENSE
django_cropperjs2-0.0.7.dist-info/METADATA
django_cropperjs2-0.0.7.dist-info/WHEEL
django_cropperjs2-0.0.7.dist-info/top_level.txt
django_cropperjs2-0.0.7.dist-info/RECORD
